[
  {
    "id": "wefoewjfojewopfqwe",
    "uid": "ewdeflbjrpap",
    "name": "히히",
    "userImage": "https://lh3.googleusercontent.com/a/ACg8ocJ-01dBbJS4T52rwT4OuIt720t--uF0QG5ahHM72am_=s96-c",
    "title": "강아지 왜 많이 먹냐?",
    "content": "sefmseifmesfmsefolefmisemf",
    "contentImage": "/profile.jpg",
    "viewCount": 0,
    "commentCount": 4,
    "likeCount": 0,
    "createdAt": 1712843583686
  },
  {
    "id": "qsldbmxmr",
    "uid": "fqavqeflbjrpap",
    "name": "호호",
    "userImage": "https://lh3.googleusercontent.com/a/ACg8ocJ-01dBbJS4T52rwT4OuIt720t--uF0QG5ahHM72am_=s96-c",
    "title": "강아지 왜 오래 자냐?",
    "content": "sefmseifmesfmsefolefmisemf",
    "viewCount": 2,
    "commentCount": 2,
    "likeCount": 4,
    "createdAt": 1712843582686
  },
  {
    "id": "ekwkbrppbkw",
    "uid": "lvkpepweflbjrpap",
    "name": "하이",
    "title": "강아지 왜 오래 자냐?",
    "content": "sefmseifmesfmsefolefmisemf",
    "contentImage": "/profile.jpg",
    "viewCount": 10,
    "commentCount": 0,
    "likeCount": 4,
    "createdAt": 1712843483686
  },
  {
    "id": "tnkglkvkpds",
    "uid": "nffbot",
    "name": "아아아",
    "title": "강아지??",
    "content": "가느다란 물방울",
    "viewCount": 1,
    "commentCount": 1,
    "likeCount": 0,
    "createdAt": 1712843583186
  },
  {
    "id": "kkvfptnkglkvkpds",
    "uid": "eflbjrpap",
    "name": "쿠쿠라쿠",
    "userImage": "https://lh3.googleusercontent.com/a/ACg8ocJ-01dBbJS4T52rwT4OuIt720t--uF0QG5ahHM72am_=s96-c",
    "title": "강아지 귀여워",
    "content": "호로로로로로로로로로로 로로로롤 오로로로로로로 우루루루루루 아라라라라라라라라라라 레레레레레레레",
    "viewCount": 2,
    "commentCount": 6,
    "likeCount": 1,
    "createdAt": 1712847583686
  }
]
